<chunk name="Object" index="0">
  <items count="2">
    <item name="GUID" type_name="gh_guid" type_code="9">6ec39468-dae7-4ffa-a766-f2ab22a2c62e</item>
    <item name="Name" type_name="gh_string" type_code="10">Amplitude</item>
  </items>
  <chunks count="1">
    <chunk name="Container">
      <items count="4">
        <item name="Description" type_name="gh_string" type_code="10">Set the amplitude (length) of a vector.</item>
        <item name="InstanceGuid" type_name="gh_guid" type_code="9">09656342-9ffb-4446-8207-07031ba88db9</item>
        <item name="Name" type_name="gh_string" type_code="10">Amplitude</item>
        <item name="NickName" type_name="gh_string" type_code="10">Amp</item>
      </items>
      <chunks count="4">
        <chunk name="Attributes">
          <items count="2">
            <item name="Bounds" type_name="gh_drawing_rectanglef" type_code="35">
              <X>484</X>
              <Y>745</Y>
              <W>65</W>
              <H>44</H>
            </item>
            <item name="Pivot" type_name="gh_drawing_pointf" type_code="31">
              <X>515</X>
              <Y>767</Y>
            </item>
          </items>
        </chunk>
        <chunk name="param_input" index="0">
          <items count="7">
            <item name="Description" type_name="gh_string" type_code="10">Base vector</item>
            <item name="InstanceGuid" type_name="gh_guid" type_code="9">a098e783-326e-4c9a-9be6-fcc2e46179a8</item>
            <item name="Name" type_name="gh_string" type_code="10">Vector</item>
            <item name="NickName" type_name="gh_string" type_code="10">V</item>
            <item name="Optional" type_name="gh_bool" type_code="1">false</item>
            <item name="Source" index="0" type_name="gh_guid" type_code="9">7c2a77bf-52d1-48fa-934b-3fb59fc8a4a4</item>
            <item name="SourceCount" type_name="gh_int32" type_code="3">1</item>
          </items>
          <chunks count="1">
            <chunk name="Attributes">
              <items count="2">
                <item name="Bounds" type_name="gh_drawing_rectanglef" type_code="35">
                  <X>486</X>
                  <Y>747</Y>
                  <W>14</W>
                  <H>20</H>
                </item>
                <item name="Pivot" type_name="gh_drawing_pointf" type_code="31">
                  <X>494.5</X>
                  <Y>757</Y>
                </item>
              </items>
            </chunk>
          </chunks>
        </chunk>
        <chunk name="param_input" index="1">
          <items count="7">
            <item name="Description" type_name="gh_string" type_code="10">Amplitude (length) value</item>
            <item name="InstanceGuid" type_name="gh_guid" type_code="9">31bea616-7da8-44eb-8d1a-dd2a4919001e</item>
            <item name="Name" type_name="gh_string" type_code="10">Amplitude</item>
            <item name="NickName" type_name="gh_string" type_code="10">A</item>
            <item name="Optional" type_name="gh_bool" type_code="1">false</item>
            <item name="Source" index="0" type_name="gh_guid" type_code="9">7dda7eb1-de37-4f5f-b72e-0a55dd836fd1</item>
            <item name="SourceCount" type_name="gh_int32" type_code="3">1</item>
          </items>
          <chunks count="2">
            <chunk name="Attributes">
              <items count="2">
                <item name="Bounds" type_name="gh_drawing_rectanglef" type_code="35">
                  <X>486</X>
                  <Y>767</Y>
                  <W>14</W>
                  <H>20</H>
                </item>
                <item name="Pivot" type_name="gh_drawing_pointf" type_code="31">
                  <X>494.5</X>
                  <Y>777</Y>
                </item>
              </items>
            </chunk>
            <chunk name="PersistentData">
              <items count="1">
                <item name="Count" type_name="gh_int32" type_code="3">1</item>
              </items>
              <chunks count="1">
                <chunk name="Branch" index="0">
                  <items count="2">
                    <item name="Count" type_name="gh_int32" type_code="3">1</item>
                    <item name="Path" type_name="gh_string" type_code="10">{0}</item>
                  </items>
                  <chunks count="1">
                    <chunk name="Item" index="0">
                      <items count="1">
                        <item name="number" type_name="gh_double" type_code="6">1</item>
                      </items>
                    </chunk>
                  </chunks>
                </chunk>
              </chunks>
            </chunk>
          </chunks>
        </chunk>
        <chunk name="param_output" index="0">
          <items count="6">
            <item name="Description" type_name="gh_string" type_code="10">Resulting vector</item>
            <item name="InstanceGuid" type_name="gh_guid" type_code="9">b72835ad-cee7-4566-96ba-d3db01103b67</item>
            <item name="Name" type_name="gh_string" type_code="10">Vector</item>
            <item name="NickName" type_name="gh_string" type_code="10">V</item>
            <item name="Optional" type_name="gh_bool" type_code="1">false</item>
            <item name="SourceCount" type_name="gh_int32" type_code="3">0</item>
          </items>
          <chunks count="1">
            <chunk name="Attributes">
              <items count="2">
                <item name="Bounds" type_name="gh_drawing_rectanglef" type_code="35">
                  <X>530</X>
                  <Y>747</Y>
                  <W>17</W>
                  <H>40</H>
                </item>
                <item name="Pivot" type_name="gh_drawing_pointf" type_code="31">
                  <X>538.5</X>
                  <Y>767</Y>
                </item>
              </items>
            </chunk>
          </chunks>
        </chunk>
      </chunks>
    </chunk>
  </chunks>
</chunk>