<chunk name="Object" index="0">
  <items count="2">
    <item name="GUID" type_name="gh_guid" type_code="9">4fdfe351-6c07-47ce-9fb9-be027fb62186</item>
    <item name="Name" type_name="gh_string" type_code="10">Shift List</item>
  </items>
  <chunks count="1">
    <chunk name="Container">
      <items count="5">
        <item name="Description" type_name="gh_string" type_code="10">Offset all items in a list.</item>
        <item name="Hidden" type_name="gh_bool" type_code="1">true</item>
        <item name="InstanceGuid" type_name="gh_guid" type_code="9">5d75cd3d-2f7a-4ffb-b4ba-82bb30d2d343</item>
        <item name="Name" type_name="gh_string" type_code="10">Shift List</item>
        <item name="NickName" type_name="gh_string" type_code="10">Shift</item>
      </items>
      <chunks count="5">
        <chunk name="Attributes">
          <items count="2">
            <item name="Bounds" type_name="gh_drawing_rectanglef" type_code="35">
              <X>243</X>
              <Y>772</Y>
              <W>82</W>
              <H>64</H>
            </item>
            <item name="Pivot" type_name="gh_drawing_pointf" type_code="31">
              <X>293</X>
              <Y>804</Y>
            </item>
          </items>
        </chunk>
        <chunk name="param_input" index="0">
          <items count="8">
            <item name="Access" type_name="gh_int32" type_code="3">1</item>
            <item name="Description" type_name="gh_string" type_code="10">List to shift</item>
            <item name="InstanceGuid" type_name="gh_guid" type_code="9">dbec5f39-0864-4e77-8cff-a51b2ad888c9</item>
            <item name="Name" type_name="gh_string" type_code="10">List</item>
            <item name="NickName" type_name="gh_string" type_code="10">L</item>
            <item name="Optional" type_name="gh_bool" type_code="1">false</item>
            <item name="Source" index="0" type_name="gh_guid" type_code="9">174d7dc8-35fd-4565-b4b8-64ba18da3286</item>
            <item name="SourceCount" type_name="gh_int32" type_code="3">1</item>
          </items>
          <chunks count="1">
            <chunk name="Attributes">
              <items count="2">
                <item name="Bounds" type_name="gh_drawing_rectanglef" type_code="35">
                  <X>245</X>
                  <Y>774</Y>
                  <W>33</W>
                  <H>20</H>
                </item>
                <item name="Pivot" type_name="gh_drawing_pointf" type_code="31">
                  <X>271</X>
                  <Y>784</Y>
                </item>
              </items>
            </chunk>
          </chunks>
        </chunk>
        <chunk name="param_input" index="1">
          <items count="6">
            <item name="Description" type_name="gh_string" type_code="10">Shift offset</item>
            <item name="InstanceGuid" type_name="gh_guid" type_code="9">95c0b3a9-0685-4d8d-bbb0-52fd2cabd862</item>
            <item name="Name" type_name="gh_string" type_code="10">Shift</item>
            <item name="NickName" type_name="gh_string" type_code="10">S</item>
            <item name="Optional" type_name="gh_bool" type_code="1">false</item>
            <item name="SourceCount" type_name="gh_int32" type_code="3">0</item>
          </items>
          <chunks count="2">
            <chunk name="Attributes">
              <items count="2">
                <item name="Bounds" type_name="gh_drawing_rectanglef" type_code="35">
                  <X>245</X>
                  <Y>794</Y>
                  <W>33</W>
                  <H>20</H>
                </item>
                <item name="Pivot" type_name="gh_drawing_pointf" type_code="31">
                  <X>271</X>
                  <Y>804</Y>
                </item>
              </items>
            </chunk>
            <chunk name="PersistentData">
              <items count="1">
                <item name="Count" type_name="gh_int32" type_code="3">1</item>
              </items>
              <chunks count="1">
                <chunk name="Branch" index="0">
                  <items count="2">
                    <item name="Count" type_name="gh_int32" type_code="3">1</item>
                    <item name="Path" type_name="gh_string" type_code="10">{0}</item>
                  </items>
                  <chunks count="1">
                    <chunk name="Item" index="0">
                      <items count="1">
                        <item name="number" type_name="gh_int32" type_code="3">1</item>
                      </items>
                    </chunk>
                  </chunks>
                </chunk>
              </chunks>
            </chunk>
          </chunks>
        </chunk>
        <chunk name="param_input" index="2">
          <items count="7">
            <item name="Description" type_name="gh_string" type_code="10">Wrap values</item>
            <item name="InstanceGuid" type_name="gh_guid" type_code="9">a2531598-dc4a-4785-b7c5-633cb905fe4c</item>
            <item name="InvertBooleans" type_name="gh_bool" type_code="1">true</item>
            <item name="Name" type_name="gh_string" type_code="10">Wrap</item>
            <item name="NickName" type_name="gh_string" type_code="10">W</item>
            <item name="Optional" type_name="gh_bool" type_code="1">false</item>
            <item name="SourceCount" type_name="gh_int32" type_code="3">0</item>
          </items>
          <chunks count="2">
            <chunk name="Attributes">
              <items count="2">
                <item name="Bounds" type_name="gh_drawing_rectanglef" type_code="35">
                  <X>245</X>
                  <Y>814</Y>
                  <W>33</W>
                  <H>20</H>
                </item>
                <item name="Pivot" type_name="gh_drawing_pointf" type_code="31">
                  <X>271</X>
                  <Y>824</Y>
                </item>
              </items>
            </chunk>
            <chunk name="PersistentData">
              <items count="1">
                <item name="Count" type_name="gh_int32" type_code="3">1</item>
              </items>
              <chunks count="1">
                <chunk name="Branch" index="0">
                  <items count="2">
                    <item name="Count" type_name="gh_int32" type_code="3">1</item>
                    <item name="Path" type_name="gh_string" type_code="10">{0}</item>
                  </items>
                  <chunks count="1">
                    <chunk name="Item" index="0">
                      <items count="1">
                        <item name="boolean" type_name="gh_bool" type_code="1">true</item>
                      </items>
                    </chunk>
                  </chunks>
                </chunk>
              </chunks>
            </chunk>
          </chunks>
        </chunk>
        <chunk name="param_output" index="0">
          <items count="7">
            <item name="Access" type_name="gh_int32" type_code="3">1</item>
            <item name="Description" type_name="gh_string" type_code="10">Shifted list</item>
            <item name="InstanceGuid" type_name="gh_guid" type_code="9">6ddd9033-5ac8-4885-9208-e36851aa4a4a</item>
            <item name="Name" type_name="gh_string" type_code="10">List</item>
            <item name="NickName" type_name="gh_string" type_code="10">L</item>
            <item name="Optional" type_name="gh_bool" type_code="1">false</item>
            <item name="SourceCount" type_name="gh_int32" type_code="3">0</item>
          </items>
          <chunks count="1">
            <chunk name="Attributes">
              <items count="2">
                <item name="Bounds" type_name="gh_drawing_rectanglef" type_code="35">
                  <X>308</X>
                  <Y>774</Y>
                  <W>15</W>
                  <H>60</H>
                </item>
                <item name="Pivot" type_name="gh_drawing_pointf" type_code="31">
                  <X>315.5</X>
                  <Y>804</Y>
                </item>
              </items>
            </chunk>
          </chunks>
        </chunk>
      </chunks>
    </chunk>
  </chunks>
</chunk>